[
null,
{"id":1,"battlerName":"main","characterIndex":0,"characterName":"main","classId":5,"equips":[0,0,0,0,0],"faceIndex":0,"faceName":"Main","traits":[],"initialLevel":1,"maxLevel":5,"name":"MC","nickname":"","note":"","profile":""},
{"id":2,"battlerName":"","characterIndex":0,"characterName":"","classId":1,"equips":[0,0,0,0,0],"faceIndex":0,"faceName":"","traits":[],"initialLevel":1,"maxLevel":99,"name":"Cutscene","nickname":"","note":"","profile":""},
{"id":3,"battlerName":"alex_bestfriend","characterIndex":0,"characterName":"alex_bestfriend","classId":1,"equips":[0,0,0,0,0],"faceIndex":0,"faceName":"alex_bestfriend","traits":[],"initialLevel":1,"maxLevel":99,"name":"Alex","nickname":"","note":"","profile":""},
{"id":4,"battlerName":"","characterIndex":0,"characterName":"","classId":1,"equips":[0,0,0,0,0],"faceIndex":0,"faceName":"","traits":[],"initialLevel":1,"maxLevel":99,"name":"","nickname":"","note":"","profile":""},
{"id":5,"battlerName":"","characterIndex":0,"characterName":"","classId":1,"equips":[0,0,0,0,0],"faceIndex":0,"faceName":"","traits":[],"initialLevel":1,"maxLevel":99,"name":"","nickname":"","note":"","profile":""},
{"id":6,"battlerName":"","characterIndex":0,"characterName":"","classId":1,"equips":[0,0,0,0,0],"faceIndex":0,"faceName":"","traits":[],"initialLevel":1,"maxLevel":99,"name":"","nickname":"","note":"","profile":""},
{"id":7,"battlerName":"","characterIndex":0,"characterName":"","classId":1,"equips":[0,0,0,0,0],"faceIndex":0,"faceName":"","traits":[],"initialLevel":1,"maxLevel":99,"name":"","nickname":"","note":"","profile":""},
{"id":8,"battlerName":"","characterIndex":0,"characterName":"","classId":1,"equips":[0,0,0,0,0],"faceIndex":0,"faceName":"","traits":[],"initialLevel":1,"maxLevel":99,"name":"","nickname":"","note":"","profile":""},
{"id":9,"battlerName":"","characterIndex":0,"characterName":"","classId":1,"equips":[0,0,0,0,0],"faceIndex":0,"faceName":"","traits":[],"initialLevel":1,"maxLevel":99,"name":"","nickname":"","note":"","profile":""},
{"id":10,"battlerName":"","characterIndex":0,"characterName":"","classId":1,"equips":[0,0,0,0,0],"faceIndex":0,"faceName":"","traits":[],"initialLevel":1,"maxLevel":99,"name":"","nickname":"","note":"","profile":""},
{"id":11,"battlerName":"","characterIndex":0,"characterName":"","classId":1,"equips":[0,0,0,0,0],"faceIndex":0,"faceName":"","traits":[],"initialLevel":1,"maxLevel":99,"name":"","nickname":"","note":"","profile":""},
{"id":12,"battlerName":"","characterIndex":0,"characterName":"","classId":1,"equips":[0,0,0,0,0],"faceIndex":0,"faceName":"","traits":[],"initialLevel":1,"maxLevel":99,"name":"","nickname":"","note":"","profile":""},
{"id":13,"battlerName":"","characterIndex":0,"characterName":"","classId":1,"equips":[0,0,0,0,0],"faceIndex":0,"faceName":"","traits":[],"initialLevel":1,"maxLevel":99,"name":"","nickname":"","note":"","profile":""},
{"id":14,"battlerName":"","characterIndex":0,"characterName":"","classId":1,"equips":[0,0,0,0,0],"faceIndex":0,"faceName":"","traits":[],"initialLevel":1,"maxLevel":99,"name":"","nickname":"","note":"","profile":""},
{"id":15,"battlerName":"","characterIndex":0,"characterName":"","classId":1,"equips":[0,0,0,0,0],"faceIndex":0,"faceName":"","traits":[],"initialLevel":1,"maxLevel":99,"name":"","nickname":"","note":"","profile":""},
{"id":16,"battlerName":"","characterIndex":0,"characterName":"","classId":1,"equips":[0,0,0,0,0],"faceIndex":0,"faceName":"","traits":[],"initialLevel":1,"maxLevel":99,"name":"","nickname":"","note":"","profile":""},
{"id":17,"battlerName":"","characterIndex":0,"characterName":"","classId":1,"equips":[0,0,0,0,0],"faceIndex":0,"faceName":"","traits":[],"initialLevel":1,"maxLevel":99,"name":"","nickname":"","note":"","profile":""},
{"id":18,"battlerName":"","characterIndex":0,"characterName":"","classId":1,"equips":[0,0,0,0,0],"faceIndex":0,"faceName":"","traits":[],"initialLevel":1,"maxLevel":99,"name":"","nickname":"","note":"","profile":""},
{"id":19,"battlerName":"","characterIndex":0,"characterName":"","classId":1,"equips":[0,0,0,0,0],"faceIndex":0,"faceName":"","traits":[],"initialLevel":1,"maxLevel":99,"name":"","nickname":"","note":"","profile":""},
{"id":20,"battlerName":"","characterIndex":0,"characterName":"","classId":1,"equips":[0,0,0,0,0],"faceIndex":0,"faceName":"","traits":[],"initialLevel":1,"maxLevel":99,"name":"","nickname":"","note":"","profile":""}
]